odoo/addons/website_event_questions_free_text/README.rst
odoo/addons/website_event_questions_free_text/__init__.py
odoo/addons/website_event_questions_free_text/__manifest__.py
odoo/addons/website_event_questions_free_text/controllers/__init__.py
odoo/addons/website_event_questions_free_text/controllers/main.py
odoo/addons/website_event_questions_free_text/i18n/ca.po
odoo/addons/website_event_questions_free_text/i18n/ca_ES.po
odoo/addons/website_event_questions_free_text/i18n/es.po
odoo/addons/website_event_questions_free_text/i18n/it.po
odoo/addons/website_event_questions_free_text/i18n/website_event_questions_free_text.pot
odoo/addons/website_event_questions_free_text/models/__init__.py
odoo/addons/website_event_questions_free_text/models/event_event.py
odoo/addons/website_event_questions_free_text/readme/CONFIGURE.rst
odoo/addons/website_event_questions_free_text/readme/CONTRIBUTORS.rst
odoo/addons/website_event_questions_free_text/readme/DESCRIPTION.rst
odoo/addons/website_event_questions_free_text/readme/ROADMAP.rst
odoo/addons/website_event_questions_free_text/readme/USAGE.rst
odoo/addons/website_event_questions_free_text/security/ir.model.access.csv
odoo/addons/website_event_questions_free_text/static/description/icon.png
odoo/addons/website_event_questions_free_text/static/description/index.html
odoo/addons/website_event_questions_free_text/tests/__init__.py
odoo/addons/website_event_questions_free_text/tests/test_free_text.py
odoo/addons/website_event_questions_free_text/views/event_event_views.xml
odoo/addons/website_event_questions_free_text/views/event_templates.xml
odoo13_addon_website_event_questions_free_text-13.0.1.0.1.dev13.dist-info/METADATA
odoo13_addon_website_event_questions_free_text-13.0.1.0.1.dev13.dist-info/WHEEL
odoo13_addon_website_event_questions_free_text-13.0.1.0.1.dev13.dist-info/top_level.txt
odoo13_addon_website_event_questions_free_text-13.0.1.0.1.dev13.dist-info/RECORD
